edgeintelligence/__init__.py
edge_intelligence-0.1.0.dist-info/METADATA
edge_intelligence-0.1.0.dist-info/WHEEL
edge_intelligence-0.1.0.dist-info/top_level.txt
edge_intelligence-0.1.0.dist-info/RECORD
